neuroslides/__init__.py
neuroslides/neuro.py
neuroslides-0.1.1.dist-info/METADATA
neuroslides-0.1.1.dist-info/WHEEL
neuroslides-0.1.1.dist-info/top_level.txt
neuroslides-0.1.1.dist-info/RECORD
