Metadata-Version: 2.1
Name: neuroslides
Version: 0.1.1
Summary: A python package to generate slides for neuroslides presentations
Author: Muhammad Saboor Islam
Author-email: muhammadsaboor119@gmail.com
Classifier: Programming Language :: Python :: 3
Classifier: Operating System :: OS Independent
Requires-Python: >=3.6
Requires-Dist: requests
Requires-Dist: python-dotenv
